tableau_report_gen/__init__.py
tableau_report_gen/app.py
tableau_report_gen/launcher.py
tableau_report_gen/components/__init__.py
tableau_report_gen/components/uploader.py
tableau_report_gen/parser/__init__.py
tableau_report_gen/parser/tableau_parser.py
tableau_report_gen/reports/__init__.py
tableau_report_gen/reports/templates/__init__.py
tableau_report_gen/utils/__init__.py
tableau_report_gen/utils/dag.py
tableau_report_gen/utils/helpers.py
tableau_report_gen/utils/report.py
tableau_report_gen-0.1.1.dist-info/LICENSE
tableau_report_gen-0.1.1.dist-info/METADATA
tableau_report_gen-0.1.1.dist-info/WHEEL
tableau_report_gen-0.1.1.dist-info/entry_points.txt
tableau_report_gen-0.1.1.dist-info/top_level.txt
tableau_report_gen-0.1.1.dist-info/RECORD
