Metadata-Version: 2.1
Name: tableau-report-gen
Version: 0.1.1
Summary: A tool to generate reports from Tableau workbooks.
Home-page: https://github.com/ndthong2411/tableau-report-gen/tree/dev
Author: Vinh, Thong
Author-email: hovinh39@gmail.com,ndthong2411@gmail.com
Classifier: Programming Language :: Python :: 3
Classifier: License :: OSI Approved :: MIT License
Classifier: Operating System :: OS Independent
Requires-Python: >=3.12
License-File: LICENSE
Requires-Dist: streamlit
Requires-Dist: pandas
Requires-Dist: logzero
Requires-Dist: networkx
Requires-Dist: graphviz
Requires-Dist: tableauhyperapi
Requires-Dist: xhtml2pdf
